racplusplus/__init__.py
racplusplus/_racplusplus.cp310-win32.pyd
racplusplus/_racplusplus.cpp
racplusplus/_racplusplus.h
racplusplus/Eigen/Cholesky
racplusplus/Eigen/CholmodSupport
racplusplus/Eigen/Core
racplusplus/Eigen/Dense
racplusplus/Eigen/Eigen
racplusplus/Eigen/Eigenvalues
racplusplus/Eigen/Geometry
racplusplus/Eigen/Householder
racplusplus/Eigen/IterativeLinearSolvers
racplusplus/Eigen/Jacobi
racplusplus/Eigen/KLUSupport
racplusplus/Eigen/LU
racplusplus/Eigen/MetisSupport
racplusplus/Eigen/OrderingMethods
racplusplus/Eigen/PaStiXSupport
racplusplus/Eigen/PardisoSupport
racplusplus/Eigen/QR
racplusplus/Eigen/QtAlignedMalloc
racplusplus/Eigen/SPQRSupport
racplusplus/Eigen/SVD
racplusplus/Eigen/Sparse
racplusplus/Eigen/SparseCholesky
racplusplus/Eigen/SparseCore
racplusplus/Eigen/SparseLU
racplusplus/Eigen/SparseQR
racplusplus/Eigen/StdDeque
racplusplus/Eigen/StdList
racplusplus/Eigen/StdVector
racplusplus/Eigen/SuperLUSupport
racplusplus/Eigen/UmfPackSupport
racplusplus/Eigen/src/Cholesky/LDLT.h
racplusplus/Eigen/src/Cholesky/LLT.h
racplusplus/Eigen/src/Cholesky/LLT_LAPACKE.h
racplusplus/Eigen/src/CholmodSupport/CholmodSupport.h
racplusplus/Eigen/src/Core/ArithmeticSequence.h
racplusplus/Eigen/src/Core/Array.h
racplusplus/Eigen/src/Core/ArrayBase.h
racplusplus/Eigen/src/Core/ArrayWrapper.h
racplusplus/Eigen/src/Core/Assign.h
racplusplus/Eigen/src/Core/AssignEvaluator.h
racplusplus/Eigen/src/Core/Assign_MKL.h
racplusplus/Eigen/src/Core/BandMatrix.h
racplusplus/Eigen/src/Core/Block.h
racplusplus/Eigen/src/Core/BooleanRedux.h
racplusplus/Eigen/src/Core/CommaInitializer.h
racplusplus/Eigen/src/Core/ConditionEstimator.h
racplusplus/Eigen/src/Core/CoreEvaluators.h
racplusplus/Eigen/src/Core/CoreIterators.h
racplusplus/Eigen/src/Core/CwiseBinaryOp.h
racplusplus/Eigen/src/Core/CwiseNullaryOp.h
racplusplus/Eigen/src/Core/CwiseTernaryOp.h
racplusplus/Eigen/src/Core/CwiseUnaryOp.h
racplusplus/Eigen/src/Core/CwiseUnaryView.h
racplusplus/Eigen/src/Core/DenseBase.h
racplusplus-0.1.1.dist-info/LICENSE
racplusplus-0.1.1.dist-info/METADATA
racplusplus-0.1.1.dist-info/WHEEL
racplusplus-0.1.1.dist-info/top_level.txt
racplusplus-0.1.1.dist-info/RECORD
